pycas/__init__.py
pycas/__main__.py
pycas/config.py
pycas/logger.py
pycasm-1.0.8.dist-info/LICENSE
pycasm-1.0.8.dist-info/METADATA
pycasm-1.0.8.dist-info/WHEEL
pycasm-1.0.8.dist-info/entry_points.txt
pycasm-1.0.8.dist-info/top_level.txt
pycasm-1.0.8.dist-info/RECORD
