Metadata-Version: 2.1
Name: pycasm
Version: 1.0.8
Summary: a helper for casmooc.com self-study
Home-page: https://github.com/huxulm
Author: Huxulm
Author-email: huxulm@gmail.com
License: MIT
Classifier: Development Status :: 4 - Beta
Classifier: License :: OSI Approved :: MIT License
Classifier: Programming Language :: Python :: 3.7
Classifier: Programming Language :: Python :: 3.8
Classifier: Programming Language :: Python :: 3.9
Classifier: Programming Language :: Python :: 3.10
Classifier: Programming Language :: Python :: 3 :: Only
Classifier: Natural Language :: Chinese (Simplified)
License-File: LICENSE
Requires-Dist: rich
Requires-Dist: pyyaml
Requires-Dist: certifi ==2024.7.4
Requires-Dist: charset-normalizer ==3.3.2
Requires-Dist: idna ==3.7
Requires-Dist: python-utils ==3.8.2
Requires-Dist: requests ==2.32.3
Requires-Dist: typing-extensions ==4.12.2
Requires-Dist: urllib3 ==2.2.2
